gaiohttp_websocket.py
gaiohttp_websocket-0.1.1.dist-info/DESCRIPTION.rst
gaiohttp_websocket-0.1.1.dist-info/METADATA
gaiohttp_websocket-0.1.1.dist-info/RECORD
gaiohttp_websocket-0.1.1.dist-info/WHEEL
gaiohttp_websocket-0.1.1.dist-info/metadata.json
gaiohttp_websocket-0.1.1.dist-info/top_level.txt
