Metadata-Version: 2.0
Name: gaiohttp-websocket
Version: 0.1.1
Summary: Asyncio websockets for gunicorn.
Home-page: https://github.com/urbaniak/gaiohttp-websocket
Author: Krzysztof Urbaniak
Author-email: urban@fail.pl
License: BSD
Platform: any
Classifier: Environment :: Web Environment
Classifier: Intended Audience :: Developers
Classifier: License :: OSI Approved :: BSD License
Classifier: Operating System :: OS Independent
Classifier: Programming Language :: Python
Classifier: Topic :: Internet :: WWW/HTTP :: Dynamic Content
Requires-Dist: aiohttp
Requires-Dist: gunicorn
